Sensor.v
module Sensor(input clk,input sensor,output reg [7:0] JA,output reg [6:0] led);
reg [1:0] filtro;
reg [31:0] CR,CG,CB,CC,A,Az,R,V,N,B;
reg [0:0] final,final2;

reg [31:0] suma;

/*
S0 = JA1 - B13
S1 = JA7 - G13
S2 = JA3 - D17
S3 = JA9 - D18
*/

function [31:0] abs;
	input [31:0] a,b;
	begin
	if(a<b)
		abs=b-a;
	else
		abs=a-b;
	end
endfunction

function [0:0] menor;
	input [31:0] a,b,c,d,e,f;
	begin
	if((a<b)&(a<c)&(a<d)&(a<e)&(a<f))
		menor=1;
	else
		menor=0;
	end
endfunction

initial
	begin
	suma=0;
	A=0;
	Az=0;
	R=0;
	V=0;
	N=0;
	B=0;
	led=6'd0;
	final=1'b0;
	final2=1'b0;
	filtro = 2'b00;
	CR =0;
	CG =0;
	CB =0;
	CC =0;
	end

always @ (posedge clk)
	if(final==1'b1 && final2==1'b0)
	begin
		CR =0;
		CG =0;
		CB =0;
		CC =0;
		final2=1'b1;
		
	end
	else
	
	if(final==1'b0 && final2==1'b1)
		begin
		final2=1'b0;
		end
	else
		begin
		case(filtro)
		2'b00:
			begin
			JA= 8'b00010001;
			CR = CR +1'b1;			
			end
		2'b01:
			begin
			JA= 8'b01010001;//Filtro Azul
			CB = CB +1'b1;
			end
		2'b10:
			begin
			JA= 8'b00010101; //Sin Filtro.
			CC = CC +1'b1; 
			end
		2'b11:
			begin
			JA= 8'b01010101; //Filtro Verde.
			CG = CG +1'b1;
			end
	endcase
		end
		
	

always @(posedge sensor)
	if(filtro < 2'b11)
		begin
		final=1'b0;
		filtro =filtro + 2'b01;
		end
	else
		begin
		filtro=2'b00;
		final=1'b1;
		end


always @ (posedge final)
	begin
	//amarillo,azul,rojo,verde,naranja,blanco.
	suma= CR+CG+CB+CC;
	A=abs(suma,32'd43056);
	Az=abs(suma,32'd55897);
	R=abs(suma,32'd49209);
	V=abs(suma,32'd42677);
	N=abs(suma,32'd36782);
	B=abs(suma,32'd25976);

	if (32'd10500<CR && CR<32'd12500 && 32'd12300<CB && CB<32'd14500 && 32'd3700<CC && CC<32'd5700 && 32'd12300<CG && CG<32'd14300)
		led=7'b0000001;//Amarillo
	if (32'd11500<CR && CR<32'd23500 && 32'd10500<CB && CB<32'd12500 && 32'd5200<CC && CC<32'd7000 && 32'd19300<CG && CG<32'd22700)
		led=7'b0000011;//Azul
	if (32'd13700<CR && CR<32'd15800 && 32'd13500<CB && CB<32'd15000 && 32'd4700<CC && CC<32'd6700 && 32'd19300<CG && CG<32'd21300)
		led=7'b0000111;//Rojo
	if (32'd19000<CR && CR<32'd21300 && 32'd14300<CB && CB<32'd16300 && 32'd5200<CC && CC<32'd7200 && 32'd17800<CG && CG<32'd18800)
		led=7'b0001111;//Verde
	if (32'd7000<CR && CR<32'd10000 && 32'd9000<CB && CB<32'd12000 && 32'd3000<CC && CC<32'd5000 && 32'd12000<CG && CG<32'd14500)
		led=7'b0011111;//Naranja
	if (32'd6000<CR && CR<32'd8500 && 32'd5000<CB && CB<32'd8000 && 32'd1000<CC && CC<32'd5000 && 32'd8000<CG && CG<32'd11000)
		led=7'b0111111;//Blanco
	end
	
endmodule

Sensor_TB.v
// BCDtoSSeg_TB.v
`timescale 1ns/1ps
`define SIMULATION

module Sensor_TB;
parameter tck              = 10;       // clock period in ns
parameter clk_freq = 1000000000 / tck; // Frequenzy in HZ

	reg 	reset; //entrada
	reg 	clk; //entrada
	reg	Sensor;

	Sensor s1(.clk(clk),.sensor(Sensor));
	/* Clocking device */
	initial begin
	        clk <= 0;
		Sensor =0;
		end
	always #(tck/2) clk <= ~clk;
	always #32 Sensor =!Sensor;


	initial begin: TEST_WAVE
		$dumpfile("Sensor_TB.vcd");
		$dumpvars(-1, s1);
/*	
	#0  reset = 1;
//	#1 
	Sensor = 0;
	#32 reset = 0;
	while ($time < 500) begin
		sensor=!sensor;
		#32
		end
*/

/*
	#1 Sensor = 1;
	#32 Sensor = 0;
	#32 Sensor = 1;
	#32 Sensor = 0;
	#32 Sensor = 1;
	#32 Sensor = 0;
*/

	#(tck*200)$finish; //tiempo simulación
	end

endmodule

simulation/Sensor_TB.vcd
$date
	Wed Nov  9 08:37:14 2016
$end
$version
	Icarus Verilog
$end
$timescale
	1ps
$end
$scope module Sensor_TB $end
$scope module s1 $end
$var wire 1 ! clk $end
$var wire 1 " sensor $end
$var reg 32 # A [31:0] $end
$var reg 32 $ Az [31:0] $end
$var reg 32 % B [31:0] $end
$var reg 32 & CB [31:0] $end
$var reg 32 ' CC [31:0] $end
$var reg 32 ( CG [31:0] $end
$var reg 32 ) CR [31:0] $end
$var reg 8 * JA [7:0] $end
$var reg 32 + N [31:0] $end
$var reg 32 , R [31:0] $end
$var reg 32 - V [31:0] $end
$var reg 2 . filtro [1:0] $end
$var reg 1 / final $end
$var reg 1 0 final2 $end
$var reg 7 1 led [6:0] $end
$var reg 32 2 suma [31:0] $end
$scope function abs $end
$var reg 32 3 a [31:0] $end
$var reg 32 4 abs [31:0] $end
$var reg 32 5 b [31:0] $end
$upscope $end
$scope function menor $end
$var reg 32 6 a [31:0] $end
$var reg 32 7 b [31:0] $end
$var reg 32 8 c [31:0] $end
$var reg 32 9 d [31:0] $end
$var reg 32 : e [31:0] $end
$var reg 32 ; f [31:0] $end
$var reg 1 < menor $end
$upscope $end
$upscope $end
$upscope $end
$enddefinitions $end
#0
$dumpvars
x<
bx ;
bx :
bx 9
bx 8
bx 7
bx 6
bx 5
bx 4
bx 3
b0 2
b0 1
00
0/
b0 .
b0 -
b0 ,
b0 +
bx *
b0 )
b0 (
b0 '
b0 &
b0 %
b0 $
b0 #
0"
0!
$end
#5000
b1 )
b10001 *
1!
#10000
0!
#15000
b10 )
1!
#20000
0!
#25000
b11 )
1!
#30000
0!
#32000
b1 .
1"
#35000
b1 &
b1010001 *
1!
#40000
0!
#45000
b10 &
1!
#50000
0!
#55000
b11 &
1!
#60000
0!
#64000
0"
#65000
b100 &
1!
#70000
0!
#75000
b101 &
1!
#80000
0!
#85000
b110 &
1!
#90000
0!
#95000
b111 &
1!
#96000
b10 .
1"
#100000
0!
#105000
b1 '
b10101 *
1!
#110000
0!
#115000
b10 '
1!
#120000
0!
#125000
b11 '
1!
#128000
0"
#130000
0!
#135000
b100 '
1!
#140000
0!
#145000
b101 '
1!
#150000
0!
#155000
b110 '
1!
#160000
0!
b11 .
1"
#165000
b1 (
b1010101 *
1!
#170000
0!
#175000
b10 (
1!
#180000
0!
#185000
b11 (
1!
#190000
0!
#192000
0"
#195000
b100 (
1!
#200000
0!
#205000
b101 (
1!
#210000
0!
#215000
b110 (
1!
#220000
0!
#224000
b100000 1
1<
b10001100010100001001011110 ;
b10100010110011001111001000 :
b10111011101110000110001011 9
b11010101001110110101000110 8
b10100100001111110101001000 7
b1100011000110000000101100 6
b1100011000110000000101100 %
b10001100010100001001011110 +
b10100010110011001111001000 -
b10111011101110000110001011 ,
b11010101001110110101000110 $
b10100100001111110101001000 #
b1100011000110000000101100 4
b1100011000110000001000010 5
b10110 3
b10110 2
1/
b0 .
1"
#225000
10
b0 '
b0 &
b0 (
b0 )
1!
#230000
0!
#235000
b1 )
b10001 *
1!
#240000
0!
#245000
b10 )
1!
#250000
0!
#255000
b11 )
1!
#256000
0"
#260000
0!
#265000
b100 )
1!
#270000
0!
#275000
b101 )
1!
#280000
0!
#285000
b110 )
1!
#288000
b1 .
0/
1"
#290000
0!
#295000
00
1!
#300000
0!
#305000
b1 &
b1010001 *
1!
#310000
0!
#315000
b10 &
1!
#320000
0!
0"
#325000
b11 &
1!
#330000
0!
#335000
b100 &
1!
#340000
0!
#345000
b101 &
1!
#350000
0!
#352000
b10 .
1"
#355000
b1 '
b10101 *
1!
#360000
0!
#365000
b10 '
1!
#370000
0!
#375000
b11 '
1!
#380000
0!
#384000
0"
#385000
b100 '
1!
#390000
0!
#395000
b101 '
1!
#400000
0!
#405000
b110 '
1!
#410000
0!
#415000
b111 '
1!
#416000
b11 .
1"
#420000
0!
#425000
b1 (
b1010101 *
1!
#430000
0!
#435000
b10 (
1!
#440000
0!
#445000
b11 (
1!
#448000
0"
#450000
0!
#455000
b100 (
1!
#460000
0!
#465000
b101 (
1!
#470000
0!
#475000
b110 (
1!
#480000
0!
1<
b10001100010100001001011100 ;
b10100010110011001111000110 :
b10111011101110000110001001 9
b11010101001110110101000100 8
b10100100001111110101000110 7
b1100011000110000000101010 6
b1100011000110000000101010 %
b10001100010100001001011100 +
b10100010110011001111000110 -
b10111011101110000110001001 ,
b11010101001110110101000100 $
b10100100001111110101000110 #
b1100011000110000000101010 4
b1100011000110000001000010 5
b11000 3
b11000 2
1/
b0 .
1"
#485000
10
b0 '
b0 &
b0 (
b0 )
1!
#490000
0!
#495000
b1 )
b10001 *
1!
#500000
0!
#505000
b10 )
1!
#510000
0!
#512000
0"
#515000
b11 )
1!
#520000
0!
#525000
b100 )
1!
#530000
0!
#535000
b101 )
1!
#540000
0!
#544000
b1 .
0/
1"
#545000
00
1!
#550000
0!
#555000
b1 &
b1010001 *
1!
#560000
0!
#565000
b10 &
1!
#570000
0!
#575000
b11 &
1!
#576000
0"
#580000
0!
#585000
b100 &
1!
#590000
0!
#595000
b101 &
1!
#600000
0!
#605000
b110 &
1!
#608000
b10 .
1"
#610000
0!
#615000
b1 '
b10101 *
1!
#620000
0!
#625000
b10 '
1!
#630000
0!
#635000
b11 '
1!
#640000
0!
0"
#645000
b100 '
1!
#650000
0!
#655000
b101 '
1!
#660000
0!
#665000
b110 '
1!
#670000
0!
#672000
b11 .
1"
#675000
b1 (
b1010101 *
1!
#680000
0!
#685000
b10 (
1!
#690000
0!
#695000
b11 (
1!
#700000
0!
#704000
0"
#705000
b100 (
1!
#710000
0!
#715000
b101 (
1!
#720000
0!
#725000
b110 (
1!
#730000
0!
#735000
b111 (
1!
#736000
1<
b10001100010100001001011100 ;
b10100010110011001111000110 :
b10111011101110000110001001 9
b11010101001110110101000100 8
b10100100001111110101000110 7
b1100011000110000000101010 6
b1100011000110000000101010 4
b1100011000110000001000010 5
1/
b0 .
1"
#740000
0!
#745000
10
b0 '
b0 &
b0 (
b0 )
1!
#750000
0!
#755000
b1 )
b10001 *
1!
#760000
0!
#765000
b10 )
1!
#768000
0"
#770000
0!
#775000
b11 )
1!
#780000
0!
#785000
b100 )
1!
#790000
0!
#795000
b101 )
1!
#800000
0!
b1 .
0/
1"
#805000
00
1!
#810000
0!
#815000
b1 &
b1010001 *
1!
#820000
0!
#825000
b10 &
1!
#830000
0!
#832000
0"
#835000
b11 &
1!
#840000
0!
#845000
b100 &
1!
#850000
0!
#855000
b101 &
1!
#860000
0!
#864000
b10 .
1"
#865000
b1 '
b10101 *
1!
#870000
0!
#875000
b10 '
1!
#880000
0!
#885000
b11 '
1!
#890000
0!
#895000
b100 '
1!
#896000
0"
#900000
0!
#905000
b101 '
1!
#910000
0!
#915000
b110 '
1!
#920000
0!
#925000
b111 '
1!
#928000
b11 .
1"
#930000
0!
#935000
b1 (
b1010101 *
1!
#940000
0!
#945000
b10 (
1!
#950000
0!
#955000
b11 (
1!
#960000
0!
0"
#965000
b100 (
1!
#970000
0!
#975000
b101 (
1!
#980000
0!
#985000
b110 (
1!
#990000
0!
#992000
1<
b10001100010100001001011101 ;
b10100010110011001111000111 :
b10111011101110000110001010 9
b11010101001110110101000101 8
b10100100001111110101000111 7
b1100011000110000000101011 6
b1100011000110000000101011 %
b10001100010100001001011101 +
b10100010110011001111000111 -
b10111011101110000110001010 ,
b11010101001110110101000101 $
b10100100001111110101000111 #
b1100011000110000000101011 4
b1100011000110000001000010 5
b10111 3
b10111 2
1/
b0 .
1"
#995000
10
b0 '
b0 &
b0 (
b0 )
1!
#1000000
0!
#1005000
b1 )
b10001 *
1!
#1010000
0!
#1015000
b10 )
1!
#1020000
0!
#1024000
0"
#1025000
b11 )
1!
#1030000
0!
#1035000
b100 )
1!
#1040000
0!
#1045000
b101 )
1!
#1050000
0!
#1055000
b110 )
1!
#1056000
b1 .
0/
1"
#1060000
0!
#1065000
00
1!
#1070000
0!
#1075000
b1 &
b1010001 *
1!
#1080000
0!
#1085000
b10 &
1!
#1088000
0"
#1090000
0!
#1095000
b11 &
1!
#1100000
0!
#1105000
b100 &
1!
#1110000
0!
#1115000
b101 &
1!
#1120000
0!
b10 .
1"
#1125000
b1 '
b10101 *
1!
#1130000
0!
#1135000
b10 '
1!
#1140000
0!
#1145000
b11 '
1!
#1150000
0!
#1152000
0"
#1155000
b100 '
1!
#1160000
0!
#1165000
b101 '
1!
#1170000
0!
#1175000
b110 '
1!
#1180000
0!
#1184000
b11 .
1"
#1185000
b1 (
b1010101 *
1!
#1190000
0!
#1195000
b10 (
1!
#1200000
0!
#1205000
b11 (
1!
#1210000
0!
#1215000
b100 (
1!
#1216000
0"
#1220000
0!
#1225000
b101 (
1!
#1230000
0!
#1235000
b110 (
1!
#1240000
0!
#1245000
b111 (
1!
#1248000
1<
b10001100010100001001011100 ;
b10100010110011001111000110 :
b10111011101110000110001001 9
b11010101001110110101000100 8
b10100100001111110101000110 7
b1100011000110000000101010 6
b1100011000110000000101010 %
b10001100010100001001011100 +
b10100010110011001111000110 -
b10111011101110000110001001 ,
b11010101001110110101000100 $
b10100100001111110101000110 #
b1100011000110000000101010 4
b1100011000110000001000010 5
b11000 3
b11000 2
1/
b0 .
1"
#1250000
0!
#1255000
10
b0 '
b0 &
b0 (
b0 )
1!
#1260000
0!
#1265000
b1 )
b10001 *
1!
#1270000
0!
#1275000
b10 )
1!
#1280000
0!
0"
#1285000
b11 )
1!
#1290000
0!
#1295000
b100 )
1!
#1300000
0!
#1305000
b101 )
1!
#1310000
0!
#1312000
b1 .
0/
1"
#1315000
00
1!
#1320000
0!
#1325000
b1 &
b1010001 *
1!
#1330000
0!
#1335000
b10 &
1!
#1340000
0!
#1344000
0"
#1345000
b11 &
1!
#1350000
0!
#1355000
b100 &
1!
#1360000
0!
#1365000
b101 &
1!
#1370000
0!
#1375000
b110 &
1!
#1376000
b10 .
1"
#1380000
0!
#1385000
b1 '
b10101 *
1!
#1390000
0!
#1395000
b10 '
1!
#1400000
0!
#1405000
b11 '
1!
#1408000
0"
#1410000
0!
#1415000
b100 '
1!
#1420000
0!
#1425000
b101 '
1!
#1430000
0!
#1435000
b110 '
1!
#1440000
0!
b11 .
1"
#1445000
b1 (
b1010101 *
1!
#1450000
0!
#1455000
b10 (
1!
#1460000
0!
#1465000
b11 (
1!
#1470000
0!
#1472000
0"
#1475000
b100 (
1!
#1480000
0!
#1485000
b101 (
1!
#1490000
0!
#1495000
b110 (
1!
#1500000
0!
#1504000
1<
b10001100010100001001011101 ;
b10100010110011001111000111 :
b10111011101110000110001010 9
b11010101001110110101000101 8
b10100100001111110101000111 7
b1100011000110000000101011 6
b1100011000110000000101011 %
b10001100010100001001011101 +
b10100010110011001111000111 -
b10111011101110000110001010 ,
b11010101001110110101000101 $
b10100100001111110101000111 #
b1100011000110000000101011 4
b1100011000110000001000010 5
b10111 3
b10111 2
1/
b0 .
1"
#1505000
10
b0 '
b0 &
b0 (
b0 )
1!
#1510000
0!
#1515000
b1 )
b10001 *
1!
#1520000
0!
#1525000
b10 )
1!
#1530000
0!
#1535000
b11 )
1!
#1536000
0"
#1540000
0!
#1545000
b100 )
1!
#1550000
0!
#1555000
b101 )
1!
#1560000
0!
#1565000
b110 )
1!
#1568000
b1 .
0/
1"
#1570000
0!
#1575000
00
1!
#1580000
0!
#1585000
b1 &
b1010001 *
1!
#1590000
0!
#1595000
b10 &
1!
#1600000
0!
0"
#1605000
b11 &
1!
#1610000
0!
#1615000
b100 &
1!
#1620000
0!
#1625000
b101 &
1!
#1630000
0!
#1632000
b10 .
1"
#1635000
b1 '
b10101 *
1!
#1640000
0!
#1645000
b10 '
1!
#1650000
0!
#1655000
b11 '
1!
#1660000
0!
#1664000
0"
#1665000
b100 '
1!
#1670000
0!
#1675000
b101 '
1!
#1680000
0!
#1685000
b110 '
1!
#1690000
0!
#1695000
b111 '
1!
#1696000
b11 .
1"
#1700000
0!
#1705000
b1 (
b1010101 *
1!
#1710000
0!
#1715000
b10 (
1!
#1720000
0!
#1725000
b11 (
1!
#1728000
0"
#1730000
0!
#1735000
b100 (
1!
#1740000
0!
#1745000
b101 (
1!
#1750000
0!
#1755000
b110 (
1!
#1760000
0!
1<
b10001100010100001001011100 ;
b10100010110011001111000110 :
b10111011101110000110001001 9
b11010101001110110101000100 8
b10100100001111110101000110 7
b1100011000110000000101010 6
b1100011000110000000101010 %
b10001100010100001001011100 +
b10100010110011001111000110 -
b10111011101110000110001001 ,
b11010101001110110101000100 $
b10100100001111110101000110 #
b1100011000110000000101010 4
b1100011000110000001000010 5
b11000 3
b11000 2
1/
b0 .
1"
#1765000
10
b0 '
b0 &
b0 (
b0 )
1!
#1770000
0!
#1775000
b1 )
b10001 *
1!
#1780000
0!
#1785000
b10 )
1!
#1790000
0!
#1792000
0"
#1795000
b11 )
1!
#1800000
0!
#1805000
b100 )
1!
#1810000
0!
#1815000
b101 )
1!
#1820000
0!
#1824000
b1 .
0/
1"
#1825000
00
1!
#1830000
0!
#1835000
b1 &
b1010001 *
1!
#1840000
0!
#1845000
b10 &
1!
#1850000
0!
#1855000
b11 &
1!
#1856000
0"
#1860000
0!
#1865000
b100 &
1!
#1870000
0!
#1875000
b101 &
1!
#1880000
0!
#1885000
b110 &
1!
#1888000
b10 .
1"
#1890000
0!
#1895000
b1 '
b10101 *
1!
#1900000
0!
#1905000
b10 '
1!
#1910000
0!
#1915000
b11 '
1!
#1920000
0!
0"
#1925000
b100 '
1!
#1930000
0!
#1935000
b101 '
1!
#1940000
0!
#1945000
b110 '
1!
#1950000
0!
#1952000
b11 .
1"
#1955000
b1 (
b1010101 *
1!
#1960000
0!
#1965000
b10 (
1!
#1970000
0!
#1975000
b11 (
1!
#1980000
0!
#1984000
0"
#1985000
b100 (
1!
#1990000
0!
#1995000
b101 (
1!
